Metadata-Version: 2.1
Name: Topsis-Kriti-102003628
Version: 1.0.1
Summary: This is a Python library for handling problems related to Multiple Criteria Decision Making(MCDM)
Home-page: https://github.com/KritiBhatnagar/TOPSIS_KRITI_102003628
Author: Kriti Bhatnagar
Author-email: kritimrt30@gmail.com
License: MIT
Classifier: License :: OSI Approved :: MIT License
Classifier: Programming Language :: Python :: 3.6
Classifier: Programming Language :: Python :: 3.7
Classifier: Programming Language :: Python :: 3.8
License-File: License
